createFullBOD.py
createFullBOD-0.0.2.dist-info/LICENSE
createFullBOD-0.0.2.dist-info/METADATA
createFullBOD-0.0.2.dist-info/WHEEL
createFullBOD-0.0.2.dist-info/top_level.txt
createFullBOD-0.0.2.dist-info/RECORD
