Metadata-Version: 2.1
Name: createFullBOD
Version: 0.0.2
Summary: create full structure of BOD dinamically
Home-page: https://github.com/gspagoni/createFullBODWrapper
Author: Giampaolo Spagoni
Author-email: giampaolo.spagoni@infor.com
License: MIT
Platform: UNKNOWN
Classifier: License :: OSI Approved :: MIT License
Classifier: Programming Language :: Python :: 3
Classifier: Operating System :: OS Independent
